setup.py
apideck/__init__.py
apideck/api_client.py
apideck/configuration.py
apideck/exceptions.py
apideck/model_utils.py
apideck/rest.py
apideck/api/__init__.py
apideck/api/accounting_api.py
apideck/api/ats_api.py
apideck/api/connector_api.py
apideck/api/crm_api.py
apideck/api/ecommerce_api.py
apideck/api/file_storage_api.py
apideck/api/hris_api.py
apideck/api/issue_tracking_api.py
apideck/api/lead_api.py
apideck/api/pos_api.py
apideck/api/sms_api.py
apideck/api/vault_api.py
apideck/api/webhook_api.py
apideck/apis/__init__.py
apideck/model/__init__.py
apideck/model/accounting_customer.py
apideck/model/accounting_department.py
apideck/model/accounting_departments_filter.py
apideck/model/accounting_event_type.py
apideck/model/accounting_location.py
apideck/model/accounting_locations_filter.py
apideck/model/activities_filter.py
apideck/model/activities_sort.py
apideck/model/activity.py
apideck/model/activity_attendee.py
apideck/model/address.py
apideck/model/allocation.py
apideck/model/api.py
apideck/model/api_resource.py
apideck/model/api_resource_coverage.py
apideck/model/api_resource_coverage_coverage.py
apideck/model/api_resource_linked_resources.py
apideck/model/api_resources.py
apideck/model/api_status.py
apideck/model/apis_filter.py
apideck/model/applicant.py
apideck/model/applicant_social_links.py
apideck/model/applicant_websites.py
apideck/model/applicants_filter.py
apideck/model/application.py
apideck/model/application_stage.py
apideck/model/assignee.py
apideck/model/ats_activity.py
apideck/model/ats_event_type.py
apideck/model/attachment.py
apideck/model/attachment_reference.py
apideck/model/attachment_reference_type.py
apideck/model/auth_type.py
apideck/model/bad_request_response.py
apideck/model/balance_sheet.py
apideck/model/balance_sheet_account.py
apideck/model/balance_sheet_account_record.py
apideck/model/balance_sheet_accounts.py
apideck/model/balance_sheet_assets_account.py
apideck/model/balance_sheet_equity_account.py
apideck-1.4.7.dist-info/LICENSE
apideck-1.4.7.dist-info/METADATA
apideck-1.4.7.dist-info/WHEEL
apideck-1.4.7.dist-info/top_level.txt
apideck-1.4.7.dist-info/RECORD
