Metadata-Version: 2.1
Name: apideck
Version: 1.4.7
Summary: Apideck Python SDK
Author-email: Apideck <support@apideck.com>
Project-URL: Homepage, https://apideck.com
Project-URL: Bug Tracker, https://github.com/apideck-libraries/python-sdk/issues
Classifier: Topic :: Software Development :: Libraries :: Python Modules
Classifier: Programming Language :: Python :: 3
Classifier: License :: OSI Approved :: Apache Software License
Classifier: Operating System :: OS Independent
Requires-Python: >=3.7
License-File: LICENSE
